README.md
README.rst
leaves.py
setup.py
leaves.egg-info/PKG-INFO
leaves.egg-info/SOURCES.txt
leaves.egg-info/dependency_links.txt
leaves.egg-info/requires.txt
leaves.egg-info/top_level.txt