Metadata-Version: 1.0
Name: leaves
Version: 0.3.3
Summary: 基于rabbitmq的轻量级rpc调用封装
Home-page: https://github.com/bigpangl/leaves
Author: bigpangl
Author-email: bigpangl@163.com
License: Apache License 2.0
Keywords: rpc
Platform: UNKNOWN
